<?xml version="1.0" encoding="UTF-8"?>
<BambiJob Error="3">
	<JobPhase Duration="3"
		DeviceStatus="Setup" DeviceStatusDetails="JobIncoming" 
		NodeStatus="Ready" NodeStatusDetails="JobHeld">
		<Amount Resource="Component" Speed="0" />
		<Amount Resource="Media:Input" Speed="0"  />
		<Amount Resource="UsageCounter:Input" Speed="0"  />
	</JobPhase>
	<JobPhase Duration="5"
		DeviceStatus="Running" DeviceStatusDetails="Processing" 
		NodeStatus="InProgress" NodeStatusDetails="Processing">
		<Amount Resource="Component" Waste="true"/>
		<Amount Resource="Media:Input" Speed="0" 
		Waste="true" />
		<Amount Resource="UsageCounter:Input"  />
		</JobPhase>
	<JobPhase Duration="1000000" 
		DeviceStatus="Running" DeviceStatusDetails="Good" 
		NodeStatus="InProgress" NodeStatusDetails="Good">
		<Amount Resource="Component" Speed="525" />
		<Amount Resource="Media:Input" Speed="2100" />
		<Amount Resource="UsageCounter:Input" Speed="4200" />
		</JobPhase>
</BambiJob>
